wavefront_dispatch/__init__.py
wavefront_dispatch-0.0.2.dist-info/METADATA
wavefront_dispatch-0.0.2.dist-info/RECORD
wavefront_dispatch-0.0.2.dist-info/WHEEL
wavefront_dispatch-0.0.2.dist-info/top_level.txt
