Metadata-Version: 2.1
Name: wavefront-dispatch
Version: 0.0.2
Summary: Wavefront Python Wrapper for Dispatch
Home-page: https://github.com/dispatchframework/wavefront-dispatch-python/tree/master
Author: UNKNOWN
Author-email: UNKNOWN
License: UNKNOWN
Keywords: Wavefront Dispatch,Wavefront
Platform: UNKNOWN
Requires-Dist: wavefront-pyformance (>=0.9.2)
